Numerators/__init__.py
Numerators/__main__.py
Numerators/counter.py
nooscounterlibs-1.1.0.dist-info/LICENSE
nooscounterlibs-1.1.0.dist-info/METADATA
nooscounterlibs-1.1.0.dist-info/WHEEL
nooscounterlibs-1.1.0.dist-info/pbr.json
nooscounterlibs-1.1.0.dist-info/top_level.txt
nooscounterlibs-1.1.0.dist-info/RECORD
